trainer/__init__.py
trainer/confusion_matrix.py
trainer/data_preparation.py
trainer/main.py
trainer/model_training.py
trainer/utils.py
fai_trainer-0.5.3.dist-info/METADATA
fai_trainer-0.5.3.dist-info/WHEEL
fai_trainer-0.5.3.dist-info/entry_points.txt
fai_trainer-0.5.3.dist-info/top_level.txt
fai_trainer-0.5.3.dist-info/RECORD
