Metadata-Version: 2.4
Name: fai-trainer
Version: 0.5.3
Summary: A package for training and testing image classification models using PyTorch.
Home-page: https://github.com/webnizam/fai-trainer
Author: Nizamuddin Mohamed & Michael Statelman
Author-email: webnizam@gmail.com
Classifier: Programming Language :: Python :: 3
Classifier: Operating System :: OS Independent
Classifier: Development Status :: 3 - Alpha
Classifier: Intended Audience :: Developers
Classifier: Intended Audience :: Science/Research
Classifier: Topic :: Scientific/Engineering :: Artificial Intelligence
Requires-Python: >=3.8
Requires-Dist: torch>=1.7.0
Requires-Dist: torchvision>=0.8.0
Requires-Dist: Pillow>=8.0.0
Requires-Dist: matplotlib>=3.3.0
Requires-Dist: tqdm>=4.50.0
Requires-Dist: numpy>=1.19.0
Requires-Dist: scipy>=1.5.0
Requires-Dist: scikit-learn>=0.23.2
Requires-Dist: prettytable
Requires-Dist: natsort
Requires-Dist: fpdf
Requires-Dist: timm>=0.9.0
Provides-Extra: xpu
Requires-Dist: intel-extension-for-pytorch; extra == "xpu"
Dynamic: author
Dynamic: author-email
Dynamic: classifier
Dynamic: description
Dynamic: description-content-type
Dynamic: home-page
Dynamic: provides-extra
Dynamic: requires-dist
Dynamic: requires-python
Dynamic: summary
